server_status_parser/__init__.py
server_status_parser/parser.py
server_status_parser/utils.py
server_status_parser-0.1.1.dist-info/LICENSE
server_status_parser-0.1.1.dist-info/METADATA
server_status_parser-0.1.1.dist-info/WHEEL
server_status_parser-0.1.1.dist-info/top_level.txt
server_status_parser-0.1.1.dist-info/RECORD
