Metadata-Version: 2.2
Name: server-status-parser
Version: 0.1.1
Summary: A parser for the /server-status page of Apache
Author-email: Velyan Kolev <kolev.velyan@gmail.com>
Project-URL: Homepage, https://github.com/KolevVelyan/server-status-parser
Classifier: Programming Language :: Python :: 3
Classifier: Operating System :: OS Independent
Classifier: License :: OSI Approved :: MIT License
Requires-Python: >=3.6
License-File: LICENSE
Requires-Dist: beautifulsoup4
Requires-Dist: pandas
